resources/transformations_macro.sql
scripts/__init__.py
scripts/render_transformation.py
ddi_transformations-0.0.38.dist-info/LICENSE.txt
ddi_transformations-0.0.38.dist-info/METADATA
ddi_transformations-0.0.38.dist-info/WHEEL
ddi_transformations-0.0.38.dist-info/top_level.txt
ddi_transformations-0.0.38.dist-info/RECORD
