Metadata-Version: 2.1
Name: ddi-transformations
Version: 0.0.38
Summary: Transformations pypi package
Author-email: highradius <highradius@highradius.com>
Classifier: Programming Language :: Python :: 3
Classifier: Operating System :: OS Independent
Requires-Python: >=3.10
License-File: LICENSE.txt
